smartflash/__init__.py
smartflash/app.py
flask_smartflash-1.0.3.dist-info/LICENSE.txt
flask_smartflash-1.0.3.dist-info/METADATA
flask_smartflash-1.0.3.dist-info/WHEEL
flask_smartflash-1.0.3.dist-info/top_level.txt
flask_smartflash-1.0.3.dist-info/RECORD
