Metadata-Version: 2.1
Name: flask-smartflash
Version: 1.0.3
Summary: A modern Flask extension for beautiful flash messages with toast notifications and modal popups
Home-page: https://github.com/chimenmagoodness/flask-smartflash.git
Author: Eze CHimenma Goodness
Author-email: Your Name <your.email@example.com>
License: MIT
Project-URL: Homepage, https://github.com/yourusername/flask-smartflash
Project-URL: Documentation, https://github.com/yourusername/flask-smartflash#readme
Project-URL: Repository, https://github.com/yourusername/flask-smartflash
Project-URL: Bug Reports, https://github.com/yourusername/flask-smartflash/issues
Project-URL: Changelog, https://github.com/yourusername/flask-smartflash/blob/main/CHANGELOG.md
Keywords: flask,flash,messages,toast,popup,notifications,ui
Classifier: Development Status :: 5 - Production/Stable
Classifier: Intended Audience :: Developers
Classifier: License :: OSI Approved :: MIT License
Classifier: Operating System :: OS Independent
Classifier: Programming Language :: Python :: 3
Classifier: Programming Language :: Python :: 3.7
Classifier: Programming Language :: Python :: 3.8
Classifier: Programming Language :: Python :: 3.9
Classifier: Programming Language :: Python :: 3.10
Classifier: Programming Language :: Python :: 3.11
Classifier: Programming Language :: Python :: 3.12
Classifier: Framework :: Flask
Classifier: Topic :: Internet :: WWW/HTTP :: Dynamic Content
Classifier: Topic :: Software Development :: Libraries :: Python Modules
Classifier: Topic :: Software Development :: User Interfaces
Requires-Python: >=3.6
License-File: LICENSE.txt
Requires-Dist: Flask>=2.0.0
Provides-Extra: dev
Requires-Dist: pytest>=6.0; extra == "dev"
Requires-Dist: pytest-flask>=1.0; extra == "dev"
Requires-Dist: black>=21.0; extra == "dev"
Requires-Dist: flake8>=3.8; extra == "dev"
Requires-Dist: coverage>=5.0; extra == "dev"
